pyrpo/__init__.py
pyrpo/pyrpo.py
pyrpo-0.2.3.dist-info/AUTHORS.rst
pyrpo-0.2.3.dist-info/LICENSE
pyrpo-0.2.3.dist-info/METADATA
pyrpo-0.2.3.dist-info/WHEEL
pyrpo-0.2.3.dist-info/entry_points.txt
pyrpo-0.2.3.dist-info/top_level.txt
pyrpo-0.2.3.dist-info/RECORD
