Metadata-Version: 2.1
Name: pyrpo
Version: 0.2.3
Summary: A shell command wrapper for hg, git, bzr, svn
Home-page: https://github.com/westurner/pyrpo
Author: Wes Turner
Author-email: wes@wrd.nu
License: BSD
Keywords: pyrpo hg git bzr svn
Platform: UNKNOWN
Classifier: Development Status :: 3 - Alpha
Classifier: Intended Audience :: Developers
Classifier: License :: OSI Approved :: BSD License
Classifier: Natural Language :: English
Classifier: Programming Language :: Python :: 2
Classifier: Programming Language :: Python :: 2.7
Classifier: Programming Language :: Python :: 3
Classifier: Programming Language :: Python :: 3.7
Classifier: Programming Language :: Python :: 3.8
Requires-Dist: python-dateutil
Requires-Dist: sarge
